shannon_fano/__init__.py
shannon_fano/shannon_fano_encoding.py
shannon_fano-0.1.1.dist-info/METADATA
shannon_fano-0.1.1.dist-info/WHEEL
shannon_fano-0.1.1.dist-info/top_level.txt
shannon_fano-0.1.1.dist-info/RECORD
