Metadata-Version: 2.1
Name: shannon-fano
Version: 0.1.1
Summary: Shannon Fano Encoding library
Home-page: UNKNOWN
Author: Saksham Madan
Author-email: example@email.com
License: MIT
Platform: UNKNOWN
Classifier: Intended Audience :: Developers
Classifier: License :: OSI Approved :: MIT License
Classifier: Programming Language :: Python
Classifier: Programming Language :: Python :: 3.9
Classifier: Operating System :: OS Independent
Requires-Dist: numpy
Requires-Dist: Pillow
